rayforge/__init__.py
rayforge/app.py
rayforge/config.py
rayforge/const.py
rayforge/context.py
rayforge/debug.py
rayforge/logging_setup.py
rayforge/version.py
rayforge/worker_init.py
rayforge/camera/__init__.py
rayforge/camera/controller.py
rayforge/camera/manager.py
rayforge/camera/models/__init__.py
rayforge/camera/models/camera.py
rayforge/core/__init__.py
rayforge/core/asset.py
rayforge/core/capability.py
rayforge/core/config.py
rayforge/core/doc.py
rayforge/core/group.py
rayforge/core/hooks.py
rayforge/core/item.py
rayforge/core/layer.py
rayforge/core/library_manager.py
rayforge/core/material.py
rayforge/core/material_library.py
rayforge/core/matrix.py
rayforge/core/recipe.py
rayforge/core/recipe_manager.py
rayforge/core/source_asset.py
rayforge/core/source_asset_segment.py
rayforge/core/step.py
rayforge/core/stock.py
rayforge/core/stock_asset.py
rayforge/core/tab.py
rayforge/core/vectorization_spec.py
rayforge/core/workflow.py
rayforge/core/workpiece.py
rayforge/core/expression/__init__.py
rayforge/core/expression/context.py
rayforge/core/expression/errors.py
rayforge/core/expression/evaluator.py
rayforge/core/expression/parser.py
rayforge/core/expression/tokenizer.py
rayforge/core/expression/validator.py
rayforge/core/geo/__init__.py
rayforge/core/geo/analysis.py
rayforge/core/geo/cleanup.py
rayforge/core/geo/clipping.py
rayforge/core/geo/constants.py
rayforge/core/geo/contours.py
rayforge/core/geo/fitting.py
rayforge/core/geo/font_config.py
rayforge/core/geo/geometry.py
rayforge/core/geo/intersect.py
rayforge/core/geo/linearize.py
rayforge/core/geo/primitives.py
rayforge/core/geo/query.py
rayforge/core/geo/simplify.py
rayforge/core/geo/split.py
rayforge/core/geo/text.py
rayforge/core/geo/transform.py
rayforge/core/ops/__init__.py
rayforge/core/ops/commands.py
rayforge/core/ops/container.py
rayforge/core/ops/flip.py
rayforge/core/ops/group.py
rayforge/core/ops/timing.py
rayforge/core/sketcher/__init__.py
rayforge/core/sketcher/params.py
rayforge-1.0.dist-info/licenses/LICENSE
rayforge-1.0.dist-info/METADATA
rayforge-1.0.dist-info/WHEEL
rayforge-1.0.dist-info/entry_points.txt
rayforge-1.0.dist-info/top_level.txt
rayforge-1.0.dist-info/RECORD
