Metadata-Version: 2.4
Name: rayforge
Version: 1.0
Summary: A desktop application for laser cutting and engraving
Author-email: Samuel Abels <knipknap@gmail.com>
Project-URL: Homepage, https://github.com/barebaric/rayforge
Project-URL: Bug Tracker, https://github.com/barebaric/rayforge/issues
Classifier: Programming Language :: Python :: 3
Classifier: License :: OSI Approved :: MIT License
Classifier: Operating System :: POSIX :: Linux
Classifier: Intended Audience :: End Users/Desktop
Classifier: Intended Audience :: Manufacturing
Requires-Python: >=3.10
License-File: LICENSE
Requires-Dist: aiohttp==3.13.3
Requires-Dist: asyncudp==0.11.0
Requires-Dist: blinker==1.9.0
Requires-Dist: ezdxf==1.3.5
Requires-Dist: GitPython==3.1.44
Requires-Dist: numpy==2.3.4
Requires-Dist: opencv_python
Requires-Dist: platformdirs==4.3.6
Requires-Dist: pluggy==1.6.0
Requires-Dist: pycairo==1.28.0
Requires-Dist: pyclipper==1.3.0.post6
Requires-Dist: PyGObject==3.50.0
Requires-Dist: PyOpenGL==3.1.9
Requires-Dist: PyOpenGL_accelerate==3.1.9
Requires-Dist: pypdf==6.6.2
Requires-Dist: pyserial_asyncio==0.6
Requires-Dist: pyvips==3.0.0
Requires-Dist: PyYAML==6.0.2
Requires-Dist: scipy==1.16.3
Requires-Dist: semver==3.0.2
Requires-Dist: svgelements==1.9.6
Requires-Dist: vtracer==0.6.11
Requires-Dist: websockets==14.2
Provides-Extra: test
Requires-Dist: pytest; extra == "test"
Requires-Dist: pytest-asyncio; extra == "test"
Requires-Dist: pytest-mock; extra == "test"
Requires-Dist: pytest-cov; extra == "test"
Requires-Dist: pygobject-stubs; extra == "test"
Dynamic: license-file
